{"cameraMode":{"drawMode":0,"name":"Shaded","section":"Shading Mode"},"sceneLighting":true,"audioPlay":false,"sceneViewState":{"showFog":true,"showMaterialUpdate":false,"showSkybox":true,"showFlares":true,"showImageEffects":true,"showParticleSystems":true},"in2DMode":false,"pivot":{"x":0.8208916187286377,"y":-2.254378080368042,"z":8.936758995056153},"rotation":{"x":0.2626737952232361,"y":0.06521514058113098,"z":-0.02354120835661888,"w":0.9629473090171814},"size":7.002903938293457,"orthographic":false}